{
  "db_name": "PostgreSQL",
  "query": "\nSELECT\n    ARRAY_AGG(DISTINCT f.fiskeridir_vessel_id) AS \"fiskeridir_vessel_ids!: Vec<Option<i64>>\",\n    f.call_sign AS \"call_sign!\",\n    COALESCE(ARRAY_AGG(DISTINCT a.mmsi), '{}') AS \"mmsis!: Vec<Option<Mmsi>>\",\n    COALESCE(ARRAY_AGG(DISTINCT a.name), '{}') AS \"ais_vessel_names!: Vec<Option<String>>\",\n    COALESCE(ARRAY_AGG(DISTINCT f.name), '{}') AS \"fiskeridir_vessel_names!: Vec<Option<String>>\",\n    COALESCE(\n        ARRAY_AGG(DISTINCT f.fiskeridir_vessel_source_id),\n        '{}'\n    ) AS \"fiskeridir_vessel_source_ids!: Vec<Option<VesselSource>>\"\nFROM\n    fiskeridir_vessels AS f\n    LEFT JOIN fiskeridir_ais_vessel_mapping_whitelist w ON f.fiskeridir_vessel_id = w.fiskeridir_vessel_id\n    LEFT JOIN ais_vessels AS a ON f.call_sign = a.call_sign\nWHERE\n    (\n        w.is_manual = FALSE\n        OR w.is_manual IS NULL\n    )\n    AND f.call_sign IS NOT NULL\n    AND NOT (f.call_sign = ANY ($1::VARCHAR[]))\nGROUP BY\n    f.call_sign\nHAVING\n    COUNT(*) > 1\n            ",
  "describe": {
    "columns": [
      {
        "ordinal": 0,
        "name": "fiskeridir_vessel_ids!: Vec<Option<i64>>",
        "type_info": "Int8Array"
      },
      {
        "ordinal": 1,
        "name": "call_sign!",
        "type_info": "Varchar"
      },
      {
        "ordinal": 2,
        "name": "mmsis!: Vec<Option<Mmsi>>",
        "type_info": "Int4Array"
      },
      {
        "ordinal": 3,
        "name": "ais_vessel_names!: Vec<Option<String>>",
        "type_info": "VarcharArray"
      },
      {
        "ordinal": 4,
        "name": "fiskeridir_vessel_names!: Vec<Option<String>>",
        "type_info": "VarcharArray"
      },
      {
        "ordinal": 5,
        "name": "fiskeridir_vessel_source_ids!: Vec<Option<VesselSource>>",
        "type_info": "Int4Array"
      }
    ],
    "parameters": {
      "Left": [
        "VarcharArray"
      ]
    },
    "nullable": [
      null,
      true,
      null,
      null,
      null,
      null
    ]
  },
  "hash": "4de4e2bdf60266749601e11a4f2be0e63331a4de378bb6c896d373652cbd4b1e"
}
