{
  "db_name": "PostgreSQL",
  "query": "\nSELECT\n    catch_location_id,\n    week,\n    species_group_id AS \"species_group_id: SpeciesGroup\",\n    weight,\n    \"year\"\nFROM\n    fishing_weight_predictions\nWHERE\n    ml_model_id = $1\n    AND species_group_id = $2\n    AND week = $3\nORDER BY\n    weight DESC\nLIMIT\n    $4\n            ",
  "describe": {
    "columns": [
      {
        "ordinal": 0,
        "name": "catch_location_id",
        "type_info": "Varchar"
      },
      {
        "ordinal": 1,
        "name": "week",
        "type_info": "Int4"
      },
      {
        "ordinal": 2,
        "name": "species_group_id: SpeciesGroup",
        "type_info": "Int4"
      },
      {
        "ordinal": 3,
        "name": "weight",
        "type_info": "Float8"
      },
      {
        "ordinal": 4,
        "name": "year",
        "type_info": "Int4"
      }
    ],
    "parameters": {
      "Left": [
        "Int4",
        "Int4",
        "Int4",
        "Int8"
      ]
    },
    "nullable": [
      false,
      false,
      false,
      false,
      false
    ]
  },
  "hash": "d32cea102fce531b72003da8ffa3985958c1df3b4a047975eee25e3b88bbd2a1"
}
